mypackage/__init__.py
mypackage/main.py
mm_baka-0.0.2.dist-info/LICENSE
mm_baka-0.0.2.dist-info/METADATA
mm_baka-0.0.2.dist-info/WHEEL
mm_baka-0.0.2.dist-info/top_level.txt
mm_baka-0.0.2.dist-info/RECORD
